{
    "version": "0.9.7",
    "architecture": {
        "32bit": {
            "url": "https://github.com/hookdeck/hookdeck-cli/releases/download/v0.9.7/hookdeck_0.9.7_windows_386.tar.gz",
            "bin": [
                "hookdeck.exe"
            ],
            "hash": "b813771e2d4fafdee9a19c250cff8a31cdd42ddad65ea481a8b2f7be0f3426fa"
        },
        "64bit": {
            "url": "https://github.com/hookdeck/hookdeck-cli/releases/download/v0.9.7/hookdeck_0.9.7_windows_amd64.tar.gz",
            "bin": [
                "hookdeck.exe"
            ],
            "hash": "a563876cb085555b0e6e625ac8c21989103011118ccb41b3197d55834d0bdea1"
        }
    },
    "homepage": "https://hookdeck.com",
    "license": "Apache 2.0",
    "description": "Hookdeck CLI utility"
}