{
    "version": "0.3.4",
    "architecture": {
        "32bit": {
            "url": "https://github.com/hookdeck/hookdeck-cli/releases/download/v0.3.4/hookdeck_0.3.4_windows_i386.zip",
            "bin": [
                "hookdeck.exe"
            ],
            "hash": "8aae3531fb901e7bf423235238f9897bd8aa9c6f98687c8186c5b1307904db0f"
        },
        "64bit": {
            "url": "https://github.com/hookdeck/hookdeck-cli/releases/download/v0.3.4/hookdeck_0.3.4_windows_x86_64.zip",
            "bin": [
                "hookdeck.exe"
            ],
            "hash": "05cec60b500a438603f1d4275654b4ad4ea13a6990497ea3e926bbe5fef100c8"
        }
    },
    "homepage": "https://hookdeck.com",
    "license": "Apache 2.0",
    "description": "Hookdeck CLI utility"
}